{"category": "pedestrian", "polygon": [[810, 1468], [810, 1456], [818, 1455], [824, 1452], [826, 1440], [822, 1434], [814, 1429], [814, 1421], [821, 1410], [826, 1401], [826, 1385], [836, 1382], [840, 1372], [841, 1358], [839, 1343], [835, 1332], [831, 1322], [821, 1317], [817, 1313], [818, 1306], [811, 1298], [803, 1291], [793, 1289], [794, 1281], [793, 1271], [789, 1264], [782, 1262], [774, 1260], [766, 1263], [761, 1268], [759, 1276], [760, 1284], [763, 1293], [766, 1300], [766, 1307], [763, 1318], [762, 1333], [762, 1348], [763, 1359], [763, 1372], [762, 1389], [761, 1404], [765, 1406], [762, 1420], [761, 1438], [760, 1450], [763, 1455], [771, 1462], [782, 1472], [792, 1480], [792, 1495], [790, 1509], [785, 1515], [779, 1519], [774, 1521], [769, 1524], [770, 1529], [780, 1530], [797, 1530], [809, 1529], [811, 1525], [811, 1515], [818, 1509], [823, 1501], [827, 1496], [832, 1490], [829, 1485], [824, 1480], [817, 1473]], "camera_name": "grn43E3", "capture_date": "20171207T2024", "frame_id": 60, "keypoint": {"reye": {"y": 1283, "x": 767, "visible": true}, "head": {"y": 1267, "x": 768, "visible": true}, "lknee": {"y": 1451, "x": 787, "visible": true}, "neck": {"y": 1305, "x": 777, "visible": true}, "rwri": {"y": 1386, "x": 768, "visible": true}, "lwri": {"y": 1414, "x": 809, "visible": true}, "rknee": {"y": 1449, "x": 764, "visible": true}, "lelb": {"y": 1368, "x": 810, "visible": true}, "lsho": {"y": 1309, "x": 803, "visible": true}, "rhip": {"y": 1394, "x": 774, "visible": true}, "leye": {"y": 1282, "x": 776, "visible": true}, "lankl": {"y": 1514, "x": 801, "visible": true}, "lhip": {"y": 1392, "x": 799, "visible": true}, "mouth": {"y": 1293, "x": 771, "visible": true}, "nose": {"y": 1288, "x": 770, "visible": true}, "rankl": {"y": 1486, "x": 816, "visible": true}, "relb": {"y": 1363, "x": 767, "visible": true}, "rsho": {"y": 1310, "x": 767, "visible": true}}, "tracking_id": "15d1ab9781b84825b03a9cf713f52ed5"}