{"category": "pedestrian", "polygon": [[2436, 1388], [2434, 1393], [2431, 1397], [2430, 1400], [2430, 1404], [2429, 1407], [2431, 1411], [2434, 1412], [2439, 1410], [2438, 1418], [2436, 1430], [2435, 1435], [2435, 1440], [2435, 1449], [2435, 1457], [2437, 1461], [2438, 1465], [2437, 1469], [2434, 1471], [2432, 1474], [2434, 1476], [2437, 1476], [2441, 1476], [2445, 1476], [2451, 1476], [2454, 1476], [2454, 1472], [2456, 1469], [2458, 1461], [2459, 1451], [2459, 1445], [2460, 1443], [2462, 1441], [2462, 1434], [2462, 1426], [2460, 1421], [2459, 1416], [2459, 1414], [2462, 1414], [2465, 1412], [2465, 1406], [2465, 1399], [2462, 1397], [2464, 1391], [2461, 1386], [2453, 1383], [2452, 1375], [2448, 1373], [2445, 1373], [2441, 1375], [2441, 1380], [2439, 1383]], "camera_name": "ylw79D0", "capture_date": "20171207T2024", "frame_id": 246, "keypoint": {"reye": {"y": 1381, "x": 2443, "visible": true}, "head": {"y": 1374, "x": 2446, "visible": true}, "lknee": {"y": 1445, "x": 2454, "visible": true}, "neck": {"y": 1388, "x": 2447, "visible": true}, "rwri": {"y": 1407, "x": 2437, "visible": true}, "lwri": {"y": 1398, "x": 2449, "visible": true}, "rknee": {"y": 1442, "x": 2437, "visible": true}, "lelb": {"y": 1402, "x": 2453, "visible": true}, "lsho": {"y": 1387, "x": 2454, "visible": true}, "rhip": {"y": 1426, "x": 2439, "visible": true}, "leye": {"y": 1381, "x": 2446, "visible": true}, "lankl": {"y": 1472, "x": 2453, "visible": true}, "lhip": {"y": 1428, "x": 2459, "visible": true}, "mouth": {"y": 1385, "x": 2445, "visible": true}, "nose": {"y": 1383, "x": 2445, "visible": true}, "rankl": {"y": 1469, "x": 2444, "visible": true}, "relb": {"y": 1409, "x": 2432, "visible": true}, "rsho": {"y": 1388, "x": 2437, "visible": true}}, "tracking_id": "487325440dff487f9ff9389d16f068a4"}