{"category": "pedestrian", "polygon": null, "camera_name": "blu79CF", "capture_date": "20171207T2024", "frame_id": 204, "keypoint": {"reye": {"y": 1291, "x": 1556, "visible": true}, "head": {"y": 1288, "x": 1559, "visible": true}, "lknee": {"y": 1349, "x": 1564, "visible": true}, "neck": {"y": 1297, "x": 1559, "visible": true}, "rwri": {"y": 1314, "x": 1550, "visible": true}, "lwri": {"y": 1307, "x": 1564, "visible": true}, "rknee": {"y": 1351, "x": 1558, "visible": true}, "lelb": {"y": 1317, "x": 1570, "visible": true}, "lsho": {"y": 1302, "x": 1571, "visible": true}, "rhip": {"y": 1329, "x": 1552, "visible": true}, "leye": {"y": 1292, "x": 1560, "visible": true}, "lankl": {"y": 1369, "x": 1565, "visible": true}, "lhip": {"y": 1330, "x": 1569, "visible": true}, "mouth": {"y": 1293, "x": 1558, "visible": true}, "nose": {"y": 1292, "x": 1558, "visible": true}, "rankl": {"y": 1371, "x": 1559, "visible": true}, "relb": {"y": 1317, "x": 1546, "visible": true}, "rsho": {"y": 1301, "x": 1551, "visible": true}}, "tracking_id": "487325440dff487f9ff9389d16f068a4"}