{"category": "pedestrian", "polygon": [[1628, 1412], [1628, 1422], [1628, 1434], [1627, 1444], [1625, 1450], [1620, 1453], [1612, 1457], [1606, 1458], [1594, 1459], [1581, 1461], [1572, 1463], [1562, 1464], [1563, 1451], [1559, 1446], [1559, 1440], [1558, 1434], [1561, 1431], [1562, 1424], [1561, 1418], [1556, 1414], [1558, 1411], [1562, 1410], [1570, 1407], [1571, 1402], [1569, 1396], [1566, 1392], [1566, 1386], [1566, 1381], [1566, 1376], [1571, 1371], [1577, 1371], [1583, 1372], [1588, 1377], [1591, 1382], [1595, 1382], [1602, 1383], [1606, 1387], [1607, 1391], [1609, 1396], [1609, 1399], [1613, 1399], [1616, 1403], [1623, 1404], [1625, 1404]], "camera_name": "ylw79D0", "capture_date": "20171207T2024", "frame_id": 150, "keypoint": {"reye": {"y": 1388, "x": 1569, "visible": true}, "head": {"y": 1380, "x": 1569, "visible": true}, "lknee": {"y": 1516, "x": 1596, "visible": true}, "neck": {"y": 1397, "x": 1587, "visible": true}, "rwri": {"y": 1435, "x": 1574, "visible": true}, "lwri": {"y": 1443, "x": 1573, "visible": true}, "rknee": {"y": 1518, "x": 1566, "visible": true}, "lelb": {"y": 1443, "x": 1608, "visible": true}, "lsho": {"y": 1408, "x": 1604, "visible": true}, "rhip": {"y": 1472, "x": 1566, "visible": true}, "leye": {"y": 1386, "x": 1574, "visible": true}, "lankl": {"y": 1578, "x": 1599, "visible": true}, "lhip": {"y": 1475, "x": 1600, "visible": true}, "mouth": {"y": 1394, "x": 1572, "visible": true}, "nose": {"y": 1390, "x": 1571, "visible": true}, "rankl": {"y": 1578, "x": 1564, "visible": true}, "relb": {"y": 1434, "x": 1593, "visible": true}, "rsho": {"y": 1416, "x": 1570, "visible": true}}, "tracking_id": "19dbb4b1d8c548e18832ba5656f73ef3"}