{"category": "pedestrian", "polygon": [[95, 1537], [92, 1517], [89, 1497], [81, 1471], [79, 1457], [76, 1436], [67, 1430], [61, 1422], [53, 1406], [46, 1404], [42, 1405], [34, 1409], [24, 1410], [26, 1417], [25, 1424], [26, 1430], [30, 1436], [31, 1440], [21, 1444], [17, 1448], [12, 1453], [5, 1456], [0, 1456], [0, 1460], [0, 1468], [0, 1472], [0, 1478], [0, 1486], [0, 1490], [0, 1496], [1, 1504], [0, 1522], [0, 1537], [0, 1548], [0, 1556], [2, 1559], [15, 1559], [22, 1560], [22, 1575], [25, 1585], [29, 1598], [30, 1614], [30, 1627], [28, 1635], [24, 1637], [20, 1640], [13, 1642], [16, 1644], [29, 1646], [40, 1645], [50, 1644], [49, 1639], [48, 1625], [52, 1603], [62, 1610], [73, 1619], [80, 1623], [84, 1630], [84, 1639], [82, 1645], [87, 1647], [94, 1642], [97, 1637], [99, 1625], [105, 1618], [104, 1611], [95, 1610], [82, 1599], [75, 1591], [68, 1586], [66, 1566], [83, 1564], [92, 1556], [95, 1543]], "camera_name": "ylw79D0", "capture_date": "20171207T2024", "frame_id": 211, "keypoint": {"reye": {"y": 1422, "x": 30, "visible": true}, "head": {"y": 1412, "x": 34, "visible": true}, "lknee": {"y": 1589, "x": 29, "visible": true}, "neck": {"y": 1442, "x": 49, "visible": true}, "rwri": {"y": 1515, "x": 56, "visible": true}, "lwri": {"y": 1475, "x": 17, "visible": true}, "rknee": {"y": 1589, "x": 59, "visible": true}, "lelb": {"y": 1488, "x": 4, "visible": true}, "lsho": {"y": 1460, "x": 33, "visible": true}, "rhip": {"y": 1532, "x": 78, "visible": true}, "leye": {"y": 1422, "x": 32, "visible": true}, "lankl": {"y": 1631, "x": 39, "visible": true}, "lhip": {"y": 1533, "x": 33, "visible": true}, "mouth": {"y": 1435, "x": 32, "visible": true}, "nose": {"y": 1429, "x": 28, "visible": true}, "rankl": {"y": 1618, "x": 86, "visible": true}, "relb": {"y": 1485, "x": 71, "visible": true}, "rsho": {"y": 1454, "x": 72, "visible": true}}, "tracking_id": "442f4341bf6945c9901729b7d14e8192"}