{"category": "pedestrian", "polygon": [[1428, 1373], [1427, 1367], [1425, 1360], [1424, 1353], [1420, 1352], [1420, 1346], [1421, 1337], [1422, 1331], [1421, 1324], [1417, 1325], [1413, 1323], [1412, 1317], [1415, 1310], [1418, 1304], [1422, 1299], [1422, 1294], [1423, 1288], [1426, 1285], [1431, 1285], [1434, 1287], [1436, 1291], [1440, 1293], [1442, 1300], [1444, 1305], [1444, 1309], [1446, 1318], [1444, 1326], [1444, 1334], [1445, 1341], [1444, 1350], [1441, 1353], [1440, 1357], [1440, 1365], [1438, 1372], [1438, 1378], [1439, 1382], [1439, 1386], [1437, 1388], [1434, 1388], [1430, 1388], [1427, 1386], [1426, 1382], [1425, 1377]], "camera_name": "blu79CF", "capture_date": "20171207T2024", "frame_id": 243, "keypoint": {"reye": {"y": 1294, "x": 1426, "visible": true}, "head": {"y": 1289, "x": 1428, "visible": true}, "lknee": {"y": 1357, "x": 1435, "visible": true}, "neck": {"y": 1302, "x": 1429, "visible": true}, "rwri": {"y": 1315, "x": 1421, "visible": true}, "lwri": {"y": 1330, "x": 1440, "visible": true}, "rknee": {"y": 1358, "x": 1431, "visible": true}, "lelb": {"y": 1321, "x": 1448, "visible": true}, "lsho": {"y": 1306, "x": 1445, "visible": true}, "rhip": {"y": 1337, "x": 1425, "visible": true}, "leye": {"y": 1295, "x": 1429, "visible": true}, "lankl": {"y": 1385, "x": 1431, "visible": true}, "lhip": {"y": 1336, "x": 1435, "visible": true}, "mouth": {"y": 1300, "x": 1428, "visible": true}, "nose": {"y": 1298, "x": 1427, "visible": true}, "rankl": {"y": 1383, "x": 1436, "visible": true}, "relb": {"y": 1322, "x": 1414, "visible": true}, "rsho": {"y": 1305, "x": 1419, "visible": true}}, "tracking_id": "487325440dff487f9ff9389d16f068a4"}