{"category": "pedestrian", "polygon": [[1045, 1375], [1044, 1363], [1046, 1349], [1045, 1341], [1042, 1334], [1045, 1326], [1042, 1316], [1033, 1307], [1034, 1295], [1032, 1284], [1027, 1279], [1021, 1278], [1013, 1278], [1008, 1281], [1014, 1291], [1026, 1299], [1026, 1314], [1025, 1335], [1020, 1352], [1020, 1364], [1023, 1377], [1022, 1385], [1021, 1392], [1016, 1396], [1010, 1400], [1005, 1399], [1006, 1414], [1000, 1422], [990, 1433], [990, 1440], [994, 1448], [994, 1456], [996, 1465], [996, 1473], [992, 1479], [986, 1483], [979, 1484], [979, 1490], [987, 1489], [991, 1486], [996, 1485], [1008, 1480], [1018, 1482], [1024, 1486], [1024, 1491], [1032, 1491], [1037, 1489], [1036, 1482], [1033, 1477], [1034, 1462], [1033, 1442], [1030, 1436], [1032, 1422], [1035, 1415], [1041, 1407], [1042, 1397], [1044, 1383]], "camera_name": "grn43E3", "capture_date": "20171207T2024", "frame_id": 125, "keypoint": {"reye": {"y": 1289, "x": 1028, "visible": true}, "head": {"y": 1283, "x": 1022, "visible": true}, "lknee": {"y": 1432, "x": 1002, "visible": true}, "neck": {"y": 1309, "x": 1029, "visible": true}, "rwri": {"y": 1372, "x": 1033, "visible": true}, "lwri": {"y": 1375, "x": 1012, "visible": true}, "rknee": {"y": 1433, "x": 1022, "visible": true}, "lelb": {"y": 1354, "x": 1015, "visible": true}, "lsho": {"y": 1329, "x": 1021, "visible": true}, "rhip": {"y": 1377, "x": 1042, "visible": true}, "leye": {"y": 1290, "x": 1019, "visible": true}, "lankl": {"y": 1479, "x": 998, "visible": true}, "lhip": {"y": 1379, "x": 1018, "visible": true}, "mouth": {"y": 1298, "x": 1026, "visible": true}, "nose": {"y": 1294, "x": 1025, "visible": true}, "rankl": {"y": 1477, "x": 1029, "visible": true}, "relb": {"y": 1349, "x": 1042, "visible": true}, "rsho": {"y": 1320, "x": 1040, "visible": true}}, "tracking_id": "442f4341bf6945c9901729b7d14e8192"}